paquete/__init__.py
paquete/logger.py
colorlogterminal-0.1.0.dist-info/METADATA
colorlogterminal-0.1.0.dist-info/WHEEL
colorlogterminal-0.1.0.dist-info/top_level.txt
colorlogterminal-0.1.0.dist-info/RECORD
