Metadata-Version: 2.2
Name: colorlogterminal
Version: 0.1.0
Summary: Terminal color formatting for Python
Author: Fernando Leon Franco
Dynamic: author
Dynamic: summary
